{
  "version": "7",
  "dialect": "postgresql",
  "entries": [
    {
      "idx": 0,
      "version": "7",
      "when": 1775627918473,
      "tag": "0000_old_gwen_stacy",
      "breakpoints": true
    },
    {
      "idx": 1,
      "version": "7",
      "when": 1775638278584,
      "tag": "0001_cheerful_iron_man",
      "breakpoints": true
    },
    {
      "idx": 2,
      "version": "7",
      "when": 1775648278584,
      "tag": "0002_rich_nightcrawler",
      "breakpoints": true
    },
    {
      "idx": 3,
      "version": "7",
      "when": 1776230547383,
      "tag": "0003_high_shen",
      "breakpoints": true
    },
    {
      "idx": 4,
      "version": "7",
      "when": 1776326400000,
      "tag": "0004_fuzzy_gateway",
      "breakpoints": true
    },
    {
      "idx": 5,
      "version": "7",
      "when": 1776326400001,
      "tag": "0005_glossy_green_goblin",
      "breakpoints": true
    },
    {
      "idx": 6,
      "version": "7",
      "when": 1776326400002,
      "tag": "0006_inventory_servers",
      "breakpoints": true
    },
    {
      "idx": 7,
      "version": "7",
      "when": 1776326400003,
      "tag": "0007_plan_catalog_metadata",
      "breakpoints": true
    },
    {
      "idx": 8,
      "version": "7",
      "when": 1776326400004,
      "tag": "0008_instance_extensions_audit",
      "breakpoints": true
    },
    {
      "idx": 9,
      "version": "7",
      "when": 1776326400005,
      "tag": "0009_order_renewal_instance_link",
      "breakpoints": true
    },
    {
      "idx": 10,
      "version": "7",
      "when": 1776326400006,
      "tag": "0010_order_billing_details",
      "breakpoints": true
    },
    {
      "idx": 11,
      "version": "7",
      "when": 1776765000000,
      "tag": "0011_add_dodo_checkout_payment_method",
      "breakpoints": true
    },
    {
      "idx": 12,
      "version": "7",
      "when": 1776768600000,
      "tag": "0012_plan_pricing_dodo_sync_fields",
      "breakpoints": true
    },
    {
      "idx": 13,
      "version": "7",
      "when": 1776772200000,
      "tag": "0013_add_coingate_checkout_payment_method",
      "breakpoints": true
    },
    {
      "idx": 14,
      "version": "7",
      "when": 1777075200000,
      "tag": "0014_password_reset_tokens",
      "breakpoints": true
    },
    {
      "idx": 15,
      "version": "7",
      "when": 1777161600000,
      "tag": "0015_suspend_tickets_coupons",
      "breakpoints": true
    },
    {
      "idx": 16,
      "version": "7",
      "when": 1777168800000,
      "tag": "0016_audit_notifications_cms",
      "breakpoints": true
    }
  ]
}
